imumaster/__init__.py
imumaster/filters/EKF.py
imumaster/filters/__init__.py
imumaster/math/Quaternion.py
imumaster/math/__init__.py
imumaster-0.0.2.dist-info/LICENSE.txt
imumaster-0.0.2.dist-info/METADATA
imumaster-0.0.2.dist-info/WHEEL
imumaster-0.0.2.dist-info/top_level.txt
imumaster-0.0.2.dist-info/RECORD
