Metadata-Version: 2.1
Name: imumaster
Version: 0.0.2
Summary: This package provides different sensor fusion algorithms like Extended Kalman Filter (EKF) to estimate orientation.
Author-email: imumaster <xujunkai@imumaster.com>
Classifier: Programming Language :: Python :: 3
Classifier: License :: OSI Approved :: MIT License
Classifier: Operating System :: OS Independent
Requires-Python: >=3.6
License-File: LICENSE.txt
